{
  "UAE Residence Permit": {
    "source": "Individual country embassy websites and UAE MOFA",
    "last_verified": "April 2026",
    "exemptions": {
      "Georgia": {
        "access": "vf",
        "days": 90,
        "source": "https://www.geoconsul.gov.ge"
      },
      "Armenia": {
        "access": "vf",
        "days": 120,
        "source": "https://www.mfa.am"
      },
      "Azerbaijan": {
        "access": "ev",
        "days": 30,
        "source": "https://evisa.gov.az"
      },
      "Serbia": {
        "access": "vf",
        "days": 30,
        "source": "https://www.mfa.gov.rs"
      },
      "Bosnia and Herzegovina": {
        "access": "vf",
        "days": 30,
        "source": "https://www.mvp.gov.ba"
      },
      "Montenegro": {
        "access": "vf",
        "days": 30,
        "source": "https://www.gov.me"
      },
      "Albania": {
        "access": "vf",
        "days": 90,
        "source": "https://punetejashtme.gov.al"
      },
      "North Macedonia": {
        "access": "vf",
        "days": 15,
        "source": "https://www.mfa.gov.mk"
      },
      "Turkey": {
        "access": "ev",
        "days": 30,
        "source": "https://www.evisa.gov.tr",
        "note": "e-visa available for UAE residence permit holders regardless of nationality"
      },
      "Kyrgyzstan": {
        "access": "vf",
        "days": 30,
        "source": "https://www.mfa.gov.kg"
      },
      "Malaysia": {
        "access": "voa",
        "days": 30,
        "source": "https://www.imi.gov.my",
        "note": "Visa on arrival for UAE residents from select nationalities"
      },
      "Maldives": {
        "access": "voa",
        "days": 30,
        "source": "https://immigration.gov.mv"
      },
      "Thailand": {
        "access": "voa",
        "days": 15,
        "source": "https://www.thaiembassy.com",
        "note": "Visa on arrival for UAE residents from select nationalities"
      }
    }
  },
  "US Green Card (Permanent Resident)": {
    "source": "Individual country immigration authorities",
    "last_verified": "April 2026",
    "exemptions": {
      "Canada": {
        "access": "vf",
        "days": 180,
        "source": "https://www.canada.ca/en/immigration-refugees-citizenship.html",
        "note": "No visa required for US permanent residents traveling by air with valid Green Card"
      },
      "Mexico": {
        "access": "vf",
        "days": 180,
        "source": "https://www.inm.gob.mx",
        "note": "Valid Green Card = no visa needed"
      },
      "Costa Rica": {
        "access": "vf",
        "days": 30,
        "source": "https://www.migracion.go.cr"
      },
      "Georgia": {
        "access": "vf",
        "days": 90,
        "source": "https://www.geoconsul.gov.ge"
      },
      "Panama": {
        "access": "vf",
        "days": 30,
        "source": "https://www.migracion.gob.pa"
      },
      "Peru": {
        "access": "vf",
        "days": 180,
        "source": "https://www.migraciones.gob.pe"
      },
      "Belize": {
        "access": "vf",
        "days": 30,
        "source": "https://www.immigration.gov.bz"
      },
      "British Virgin Islands": {
        "access": "vf",
        "days": 30,
        "source": "https://bvi.gov.vg"
      },
      "Turks and Caicos": {
        "access": "vf",
        "days": 30,
        "source": "https://www.gov.tc"
      },
      "Albania": {
        "access": "vf",
        "days": 90,
        "source": "https://punetejashtme.gov.al"
      }
    }
  },
  "Schengen Residence Permit": {
    "source": "EU regulations and bilateral agreements",
    "last_verified": "April 2026",
    "exemptions": {
      "Albania": {
        "access": "vf",
        "days": 90,
        "source": "https://punetejashtme.gov.al"
      },
      "Bosnia and Herzegovina": {
        "access": "vf",
        "days": 90,
        "source": "https://www.mvp.gov.ba"
      },
      "Georgia": {
        "access": "vf",
        "days": 90,
        "source": "https://www.geoconsul.gov.ge"
      },
      "Kosovo": {
        "access": "vf",
        "days": 15,
        "source": "https://www.mfa-ks.net"
      },
      "Moldova": {
        "access": "vf",
        "days": 90,
        "source": "https://www.mfa.gov.md"
      },
      "Montenegro": {
        "access": "vf",
        "days": 30,
        "source": "https://www.gov.me"
      },
      "North Macedonia": {
        "access": "vf",
        "days": 15,
        "source": "https://www.mfa.gov.mk"
      },
      "Serbia": {
        "access": "vf",
        "days": 90,
        "source": "https://www.mfa.gov.rs"
      },
      "Turkey": {
        "access": "ev",
        "days": 90,
        "source": "https://www.evisa.gov.tr"
      },
      "Colombia": {
        "access": "vf",
        "days": 90,
        "source": "https://www.cancilleria.gov.co"
      }
    }
  },
  "UK Residence Permit (BRP)": {
    "source": "Individual country immigration authorities",
    "last_verified": "April 2026",
    "exemptions": {
      "Ireland": {
        "access": "vf",
        "days": 90,
        "source": "https://www.irishimmigration.ie",
        "note": "Short Stay Visa Waiver Programme for UK visa/permit holders from certain nationalities"
      },
      "Panama": {
        "access": "vf",
        "days": 30,
        "source": "https://www.migracion.gob.pa"
      },
      "Georgia": {
        "access": "vf",
        "days": 90,
        "source": "https://www.geoconsul.gov.ge"
      },
      "Albania": {
        "access": "vf",
        "days": 90,
        "source": "https://punetejashtme.gov.al"
      },
      "Bosnia and Herzegovina": {
        "access": "vf",
        "days": 30,
        "source": "https://www.mvp.gov.ba"
      },
      "Montenegro": {
        "access": "vf",
        "days": 30,
        "source": "https://www.gov.me"
      }
    }
  },
  "Canada Permanent Resident": {
    "source": "Individual country immigration authorities",
    "last_verified": "April 2026",
    "exemptions": {
      "Mexico": {
        "access": "vf",
        "days": 180,
        "source": "https://www.inm.gob.mx"
      },
      "Costa Rica": {
        "access": "vf",
        "days": 30,
        "source": "https://www.migracion.go.cr"
      },
      "Panama": {
        "access": "vf",
        "days": 30,
        "source": "https://www.migracion.gob.pa"
      },
      "Georgia": {
        "access": "vf",
        "days": 90,
        "source": "https://www.geoconsul.gov.ge"
      },
      "Albania": {
        "access": "vf",
        "days": 90,
        "source": "https://punetejashtme.gov.al"
      }
    }
  },
  "Valid US Visa (B1/B2)": {
    "source": "Individual country immigration authorities",
    "last_verified": "April 2026",
    "exemptions": {
      "Mexico": {
        "access": "vf",
        "days": 180,
        "source": "https://www.inm.gob.mx",
        "note": "Valid US visa holders can enter Mexico without a Mexican visa"
      },
      "Panama": {
        "access": "vf",
        "days": 30,
        "source": "https://www.migracion.gob.pa",
        "note": "Valid US visa (used or unused) allows entry"
      },
      "Costa Rica": {
        "access": "vf",
        "days": 30,
        "source": "https://www.migracion.go.cr"
      },
      "Colombia": {
        "access": "vf",
        "days": 90,
        "source": "https://www.cancilleria.gov.co",
        "note": "Valid US visa allows visa-free entry for up to 90 days"
      },
      "Georgia": {
        "access": "vf",
        "days": 90,
        "source": "https://www.geoconsul.gov.ge"
      },
      "Albania": {
        "access": "vf",
        "days": 90,
        "source": "https://punetejashtme.gov.al"
      },
      "North Macedonia": {
        "access": "vf",
        "days": 15,
        "source": "https://www.mfa.gov.mk"
      },
      "Serbia": {
        "access": "vf",
        "days": 90,
        "source": "https://www.mfa.gov.rs"
      },
      "Montenegro": {
        "access": "vf",
        "days": 30,
        "source": "https://www.gov.me"
      },
      "Bosnia and Herzegovina": {
        "access": "vf",
        "days": 30,
        "source": "https://www.mvp.gov.ba"
      },
      "Turkey": {
        "access": "ev",
        "days": 30,
        "source": "https://www.evisa.gov.tr",
        "note": "e-visa simplified for valid US visa holders"
      },
      "Philippines": {
        "access": "vf",
        "days": 7,
        "source": "https://www.dfa.gov.ph",
        "note": "7-day transit visa exemption with valid US visa"
      },
      "Dominican Republic": {
        "access": "vf",
        "days": 30,
        "source": "https://www.dgm.gob.do"
      },
      "Belize": {
        "access": "vf",
        "days": 30,
        "source": "https://www.immigration.gov.bz"
      }
    }
  },
  "Valid Schengen Visa": {
    "source": "Individual country immigration authorities and EU bilateral agreements",
    "last_verified": "April 2026",
    "exemptions": {
      "Albania": {
        "access": "vf",
        "days": 90,
        "source": "https://punetejashtme.gov.al",
        "note": "Valid multi-entry Schengen visa allows entry without Albanian visa"
      },
      "Bosnia and Herzegovina": {
        "access": "vf",
        "days": 30,
        "source": "https://www.mvp.gov.ba"
      },
      "Colombia": {
        "access": "vf",
        "days": 90,
        "source": "https://www.cancilleria.gov.co"
      },
      "Georgia": {
        "access": "vf",
        "days": 90,
        "source": "https://www.geoconsul.gov.ge"
      },
      "Kosovo": {
        "access": "vf",
        "days": 15,
        "source": "https://www.mfa-ks.net"
      },
      "Moldova": {
        "access": "vf",
        "days": 90,
        "source": "https://www.mfa.gov.md"
      },
      "Montenegro": {
        "access": "vf",
        "days": 30,
        "source": "https://www.gov.me"
      },
      "North Macedonia": {
        "access": "vf",
        "days": 15,
        "source": "https://www.mfa.gov.mk"
      },
      "Serbia": {
        "access": "vf",
        "days": 90,
        "source": "https://www.mfa.gov.rs"
      },
      "Turkey": {
        "access": "ev",
        "days": 90,
        "source": "https://www.evisa.gov.tr",
        "note": "e-visa simplified for valid Schengen visa holders"
      },
      "Romania": {
        "access": "vf",
        "days": 90,
        "source": "https://www.mae.ro",
        "note": "Valid Schengen visa allows entry (Romania is not yet in Schengen air borders)"
      },
      "Bulgaria": {
        "access": "vf",
        "days": 90,
        "source": "https://www.mfa.bg",
        "note": "Valid Schengen visa allows entry (Bulgaria joined Schengen air/sea March 2024)"
      },
      "Croatia": {
        "access": "vf",
        "days": 90,
        "source": "https://mvep.gov.hr",
        "note": "Croatia joined Schengen January 2023 \u2014 Schengen visa is valid"
      }
    }
  }
}